async_igdb/__init__.py
async_igdb/client.py
async_igdb/manager.py
async_igdb/models/__init__.py
async_igdb/models/base.py
async_igdb/models/complex/__init__.py
async_igdb/models/complex/age_rating.py
async_igdb/models/complex/character.py
async_igdb/models/complex/collection.py
async_igdb/models/complex/collection_membership.py
async_igdb/models/complex/collection_membership_type.py
async_igdb/models/complex/collection_relation.py
async_igdb/models/complex/collection_relation_type.py
async_igdb/models/complex/company.py
async_igdb/models/complex/cover_game_localization.py
async_igdb/models/complex/events_networks.py
async_igdb/models/complex/external_game.py
async_igdb/models/complex/franchise.py
async_igdb/models/complex/game.py
async_igdb/models/complex/game_engine.py
async_igdb/models/complex/game_version.py
async_igdb/models/complex/game_video.py
async_igdb/models/complex/involved_company.py
async_igdb/models/complex/language_support.py
async_igdb/models/complex/multiplayer_mode.py
async_igdb/models/complex/platform.py
async_igdb/models/complex/platform_version.py
async_igdb/models/complex/platform_version_company.py
async_igdb/models/complex/release_date.py
async_igdb/models/complex/screenshot.py
async_igdb/models/complex/search_result.py
async_igdb/models/complex/website.py
async_igdb/models/simple/__init__.py
async_igdb/models/simple/age_rating_content.py
async_igdb/models/simple/alternative_name.py
async_igdb/models/simple/artwork.py
async_igdb/models/simple/collection_type.py
async_igdb/models/simple/company_logo.py
async_igdb/models/simple/company_website.py
async_igdb/models/simple/game_engine_logo.py
async_igdb/models/simple/game_mode.py
async_igdb/models/simple/genre.py
async_igdb/models/simple/keyword.py
async_igdb/models/simple/language.py
async_igdb/models/simple/language_support_type.py
async_igdb/models/simple/mug_shot.py
async_igdb/models/simple/platform_family.py
async_igdb/models/simple/platform_logo.py
async_igdb-0.1.3.dist-info/METADATA
async_igdb-0.1.3.dist-info/WHEEL
async_igdb-0.1.3.dist-info/licenses/LICENSE
async_igdb-0.1.3.dist-info/RECORD
