Metadata-Version: 2.3
Name: async-igdb
Version: 0.1.3
Summary: Asynchronous wrapper around the IGDB API
Project-URL: Homepage, https://github.com/iTecAI/async-igdb
Project-URL: Repository, https://github.com/iTecAI/async-igdb.git
Author-email: Dax Harris <mvh3875@rit.edu>
License: MIT License
License-File: LICENSE
Keywords: api,async,igdb
Classifier: Development Status :: 2 - Pre-Alpha
Classifier: License :: OSI Approved :: MIT License
Classifier: Programming Language :: Python
Classifier: Topic :: Games/Entertainment
Requires-Python: >=3.12
Requires-Dist: httpx
Requires-Dist: pydantic
Provides-Extra: dev
Requires-Dist: pytest; extra == 'dev'
Requires-Dist: python-dotenv; extra == 'dev'
